pydex_dfre/__init__.py
pydex_dfre/cli.py
pydex_dfre/pydex_dfre.py
pydex_dfre-0.1.0.dist-info/LICENSE
pydex_dfre-0.1.0.dist-info/METADATA
pydex_dfre-0.1.0.dist-info/WHEEL
pydex_dfre-0.1.0.dist-info/entry_points.txt
pydex_dfre-0.1.0.dist-info/top_level.txt
pydex_dfre-0.1.0.dist-info/RECORD
